{
  "folder": "5QBQvcD8cm6ReC2o",
  "name": "Tachytheria",
  "type": "classFeature",
  "img": "icons/creatures/mammals/spirit-deer-herd-blue.webp",
  "system": {
    "summary": {
      "value": "Cats, gazelles, hares, creatures that are agile and quick."
    },
    "isFavored": {
      "value": false
    },
    "featureType": "projectfu.therioform",
    "data": {
      "description": "<p>You treat your <strong>Dexterity</strong> as if it were one die size higher (to a maximum of <strong>d12</strong>).</p><p>When you succeed on a Check to advance or turn back a Clock, if that Check includes <strong>Dexterity</strong>, you may fill or erase 1 additional section of that Clock.</p>"
    },
    "source": "FUTF157",
    "fuid": "tachytheria"
  },
  "effects": [
    {
      "name": "Tachytheria",
      "img": "icons/creatures/mammals/spirit-deer-herd-blue.webp",
      "origin": "Compendium.projectfu.skills.Item.WdA0rzemkQfGAMLk",
      "system": {
        "duration": {
          "event": "none",
          "interval": 1,
          "tracking": "self",
          "remaining": 1
        },
        "type": "default",
        "predicate": {
          "crisisInteraction": "none"
        },
        "rules": {
          "elements": {
            "fDXWEH50PHShxo33": {
              "type": "ruleElement",
              "trigger": {
                "_id": "IUhs1Hn2tUCpZwc2",
                "type": "renderCheckRuleTrigger",
                "eventRelation": "source",
                "checkTypes": [
                  "attribute",
                  "group",
                  "open",
                  "opposed"
                ],
                "itemGroups": [],
                "local": false,
                "identifier": ""
              },
              "_id": "fDXWEH50PHShxo33",
              "predicates": {
                "tLQswHgDWnWqBo6V": {
                  "type": "checkRulePredicate",
                  "_id": "tLQswHgDWnWqBo6V",
                  "outcome": "success",
                  "result": null,
                  "attributes": {
                    "primary": {
                      "value": "dex"
                    },
                    "secondary": {
                      "value": ""
                    }
                  }
                }
              },
              "actions": {
                "Hy79yl9RsS4iCu43": {
                  "type": "messageRuleAction",
                  "_id": "Hy79yl9RsS4iCu43",
                  "message": "<p>If this Check was used to alter a Clock, you may fill or erase 1 additional section.</p>"
                }
              }
            }
          },
          "progress": {
            "enabled": false,
            "id": "",
            "name": "",
            "current": 0,
            "max": 6,
            "style": "bar"
          },
          "stacking": {
            "progress": false,
            "duration": false,
            "increment": 1
          }
        }
      },
      "duration": {
        "rounds": 1,
        "startTime": null,
        "combat": null
      },
      "disabled": false,
      "_id": "Wc78nzv2k0QLfVCS",
      "type": "base",
      "changes": [
        {
          "key": "system.attributes.dex",
          "mode": 0,
          "value": "upgrade",
          "priority": null
        }
      ],
      "description": "<p>You are <strong>manifesting</strong> this therioform. <span>You treat your <strong>Dexterity</strong> as one die size higher (up to <strong>d12</strong>). </span>When you succeed on a Check to advance or turn back a Clock, if that Check includes <strong>Dexterity</strong>, you may fill or erase 1 additional section of that Clock.</p>",
      "tint": "#ffffff",
      "transfer": true,
      "statuses": [],
      "sort": 0,
      "flags": {
        "projectfu": {
          "Source": {
            "name": "Tachytheria",
            "actorUuid": null,
            "itemUuid": "Compendium.projectfu.skills.Item.WdA0rzemkQfGAMLk",
            "effectUuid": null,
            "fuid": "tachytheria"
          }
        }
      },
      "_stats": {
        "compendiumSource": null,
        "duplicateSource": null,
        "exportSource": null,
        "coreVersion": "13.351",
        "systemId": "projectfu",
        "systemVersion": "#{VERSION}#",
        "createdTime": 1777761772936,
        "modifiedTime": 1777761864018,
        "lastModifiedBy": "mA8SNY2rY4X5tOHa"
      },
      "_key": "!items.effects!WdA0rzemkQfGAMLk.Wc78nzv2k0QLfVCS"
    }
  ],
  "ownership": {
    "default": 0,
    "YN7AhHIwAZeH33Tw": 3,
    "BwRsFvMHAq9vUtEO": 3
  },
  "flags": {
    "core": {}
  },
  "_stats": {
    "systemId": "projectfu",
    "systemVersion": "#{VERSION}#",
    "coreVersion": "13.348",
    "createdTime": 1711428338643,
    "modifiedTime": 1767290951002,
    "lastModifiedBy": "J5B4HfVqUaCPvzGg",
    "compendiumSource": null,
    "duplicateSource": null,
    "exportSource": null
  },
  "_id": "WdA0rzemkQfGAMLk",
  "sort": 100196,
  "_key": "!items!WdA0rzemkQfGAMLk"
}
