{
  "folder": "3SZiWPJ5zkuKH7Pj",
  "name": "Hawkeye",
  "type": "skill",
  "_id": "hmDCgX5OEk5l4uXW",
  "img": "systems/projectfu/styles/static/compendium/classes/sharpshooter/sharpshooter_hawkeye.png",
  "system": {
    "subtype": {
      "value": ""
    },
    "summary": {
      "value": ""
    },
    "description": "<p>When you perform the <strong>Guard</strong> action, if you choose <strong>not</strong> to provide cover to another creature, you may choose one option: the next <strong>ranged</strong> attack you perform before the end of the current scene will deal <strong>【SL × 2】</strong> extra damage; <strong>or</strong> you may immediately perform a <strong>free attack</strong> with a <strong>bow</strong> or <strong>firearm</strong> you have equipped, treating your <strong>High Roll (HR)</strong> as <strong>0</strong> when calculating damage dealt by this attack.</p><hr /><ul><li><p><strong>You Receive:</strong> @EFFECT[Compendium.projectfu.skills.Item.enboiNabyACt4OUB]{Effect: Hawkeye (Range Weapon Up)}</p></li></ul>",
    "isFavored": {
      "value": false
    },
    "showTitleCard": {
      "value": false
    },
    "level": {
      "value": 1,
      "max": 5,
      "min": 0
    },
    "class": {
      "value": "Sharpshooter"
    },
    "useWeapon": {
      "accuracy": {
        "value": false
      },
      "damage": true,
      "hrZero": {
        "value": false
      }
    },
    "attributes": {
      "primary": {
        "value": "mig"
      },
      "secondary": {
        "value": "mig"
      }
    },
    "accuracy": {
      "value": 0
    },
    "damage": {
      "hasDamage": true,
      "value": 0,
      "type": "",
      "onRoll": "",
      "onApply": ""
    },
    "impdamage": {
      "hasImpDamage": {
        "value": false
      },
      "value": 0,
      "impType": {
        "value": "minor"
      },
      "type": {
        "value": "physical"
      }
    },
    "source": {
      "value": "FUCR205"
    },
    "rollInfo": {
      "useWeapon": {
        "hrZero": {
          "value": true
        },
        "accuracy": {
          "value": true
        },
        "damage": {
          "value": true
        }
      },
      "attributes": {
        "primary": {
          "value": "dex"
        },
        "secondary": {
          "value": "dex"
        }
      },
      "accuracy": {
        "value": 0
      },
      "damage": {
        "hasDamage": {
          "value": false
        },
        "type": {
          "value": "physical"
        },
        "value": 0
      }
    },
    "hasRoll": {
      "value": true
    },
    "hasResource": {
      "value": false
    },
    "rp": {
      "name": "Name",
      "current": 0,
      "step": 1,
      "max": 6
    },
    "defense": "def",
    "fuid": "hawkeye"
  },
  "effects": [],
  "ownership": {
    "default": 2,
    "hYECXwi6O8UUBuN4": 3,
    "BwRsFvMHAq9vUtEO": 3
  },
  "flags": {
    "core": {}
  },
  "_stats": {
    "systemId": "projectfu",
    "systemVersion": "#{VERSION}#",
    "coreVersion": "13.346",
    "createdTime": 1706506760285,
    "modifiedTime": 1744721508057,
    "lastModifiedBy": "LokWlpJRX2uVxtGn",
    "compendiumSource": null,
    "duplicateSource": null,
    "exportSource": null
  },
  "sort": 300000,
  "_key": "!items!hmDCgX5OEk5l4uXW"
}
