{
  "folder": "LWIsJLQGwkSdYYwN",
  "name": "Vismagus",
  "type": "skill",
  "_id": "affUHtuCYoDxmO4h",
  "img": "systems/projectfu/styles/static/compendium/classes/spiritist/spiritist_vismagus.png",
  "system": {
    "subtype": {
      "value": ""
    },
    "summary": {
      "value": ""
    },
    "description": "<p>When you cast a spell, if you don't have enough Mind Points to pay for its total cost, you may choose to spend <strong>twice as many</strong> Hit Points instead. You cannot use this Skill if doing so would reduce you to 0 Hit Points. If a spell cast this way would cause you to recover Hit Points, you instead recover no Hit Points (the spell functions normally on any other target).</p>",
    "isFavored": {
      "value": false
    },
    "showTitleCard": {
      "value": false
    },
    "level": {
      "value": 1,
      "max": 1,
      "min": 0
    },
    "class": {
      "value": "Spiritist"
    },
    "useWeapon": {
      "accuracy": {
        "value": false
      },
      "damage": {
        "value": false
      },
      "hrZero": {
        "value": false
      }
    },
    "attributes": {
      "primary": {
        "value": "mig"
      },
      "secondary": {
        "value": "mig"
      }
    },
    "accuracy": {
      "value": 0
    },
    "damage": {
      "hasDamage": {
        "value": false
      },
      "value": 0,
      "type": {
        "value": "physical"
      },
      "onRoll": "",
      "onApply": ""
    },
    "impdamage": {
      "hasImpDamage": {
        "value": false
      },
      "value": 0,
      "impType": {
        "value": "minor"
      },
      "type": {
        "value": "physical"
      }
    },
    "source": {
      "value": "FUCR207"
    },
    "rollInfo": {
      "useWeapon": {
        "hrZero": {
          "value": false
        },
        "accuracy": {
          "value": false
        },
        "damage": {
          "value": false
        }
      },
      "attributes": {
        "primary": {
          "value": "dex"
        },
        "secondary": {
          "value": "dex"
        }
      },
      "accuracy": {
        "value": 0
      },
      "damage": {
        "hasDamage": {
          "value": false
        },
        "type": {
          "value": "physical"
        },
        "value": 0
      }
    },
    "hasRoll": {
      "value": false
    },
    "hasResource": {
      "value": false
    },
    "rp": {
      "name": "Name",
      "current": 0,
      "step": 1,
      "max": 6
    },
    "defense": "def",
    "fuid": "vismagus"
  },
  "effects": [],
  "ownership": {
    "default": 2,
    "hYECXwi6O8UUBuN4": 3,
    "BwRsFvMHAq9vUtEO": 3
  },
  "flags": {
    "core": {}
  },
  "_stats": {
    "systemId": "projectfu",
    "systemVersion": "#{VERSION}#",
    "coreVersion": "13.346",
    "createdTime": 1706507954756,
    "modifiedTime": 1741949879818,
    "lastModifiedBy": "uG2TkwmswfdRqaAv",
    "compendiumSource": null,
    "duplicateSource": null,
    "exportSource": null
  },
  "sort": 500000,
  "_key": "!items!affUHtuCYoDxmO4h"
}
