{
  "folder": "KoamGTrOopqqmbxH",
  "name": "Bolt Resistance",
  "type": "effect",
  "img": "systems/projectfu/styles/static/affinities/icons/bolt.png",
  "system": {
    "fuid": "bolt-resistance",
    "source": ""
  },
  "effects": [
    {
      "name": "Bolt Resistance",
      "img": "systems/projectfu/styles/static/affinities/icons/bolt.png",
      "origin": "Compendium.projectfu.actor-effects.Item.QrEztsujMpK33cpj",
      "system": {
        "duration": {
          "event": "none",
          "interval": 1,
          "tracking": "self",
          "remaining": 1
        },
        "type": "default",
        "predicate": {
          "crisisInteraction": "none"
        },
        "rules": {
          "elements": {},
          "progress": {
            "enabled": false,
            "id": "",
            "name": "",
            "current": 0,
            "max": 6,
            "style": "bar"
          },
          "stacking": {
            "progress": false,
            "duration": false,
            "increment": 1
          }
        }
      },
      "duration": {
        "rounds": 1,
        "startTime": null,
        "combat": null
      },
      "disabled": false,
      "_id": "Gp1YICRCD5JycM5c",
      "type": "base",
      "changes": [
        {
          "key": "system.affinities.bolt",
          "mode": 0,
          "value": "upgrade",
          "priority": null
        }
      ],
      "description": "<p>You gain Resistance to <strong>bolt</strong> damage.</p>",
      "tint": "#ffffff",
      "transfer": true,
      "statuses": [],
      "sort": 0,
      "flags": {
        "projectfu": {
          "Source": {
            "name": "Bolt Resistance",
            "actorUuid": null,
            "itemUuid": "Compendium.projectfu.actor-effects.Item.QrEztsujMpK33cpj",
            "effectUuid": null,
            "fuid": "bolt-resistance"
          }
        }
      },
      "_stats": {
        "compendiumSource": null,
        "duplicateSource": null,
        "exportSource": null,
        "coreVersion": "13.351",
        "systemId": "projectfu",
        "systemVersion": "#{VERSION}#",
        "createdTime": 1774816136432,
        "modifiedTime": 1774816150469,
        "lastModifiedBy": "mA8SNY2rY4X5tOHa"
      },
      "_key": "!items.effects!QrEztsujMpK33cpj.Gp1YICRCD5JycM5c"
    }
  ],
  "flags": {},
  "_stats": {
    "compendiumSource": null,
    "duplicateSource": null,
    "coreVersion": "13.351",
    "systemId": "projectfu",
    "systemVersion": "#{VERSION}#",
    "createdTime": 1725750014969,
    "modifiedTime": 1774761011118,
    "lastModifiedBy": "mA8SNY2rY4X5tOHa",
    "exportSource": null
  },
  "_id": "QrEztsujMpK33cpj",
  "sort": 0,
  "ownership": {
    "default": 0,
    "dobQfkKFj2NK96cc": 3
  },
  "_key": "!items!QrEztsujMpK33cpj"
}
