{
  "folder": "NWyKWh1qGp8D9yvJ",
  "name": "Quick Scan",
  "type": "heroic",
  "img": "icons/sundries/books/book-open-purple.webp",
  "system": {
    "subtype": {
      "value": "skill"
    },
    "summary": {
      "value": "Examine multiple creatures."
    },
    "description": "<blockquote><p><strong>Requirements: </strong>you must have mastered the <strong>Loremaster</strong> Class.</p></blockquote><p>When you perform the <strong>Study</strong> action during a conflict, you may examine the <strong>profiles </strong>of <strong>all enemies</strong> you can see. If you do, you perform a single <strong>【INS + INS】</strong> Open Check and apply the Result <strong>separately</strong> to each enemy (<strong>Core Rulebook</strong>, page <strong>319</strong>).</p><p>However, this Check <strong>cannot</strong> trigger your @UUID[Compendium.projectfu.skills.Item.J5KbrSiczxizbdM3]{Flash of Insight} Skill (if you have it).</p>",
    "isFavored": {
      "value": false
    },
    "showTitleCard": {
      "value": false
    },
    "level": {
      "value": 1,
      "max": 10,
      "min": 0
    },
    "class": {
      "value": "Loremaster"
    },
    "useWeapon": {
      "accuracy": {
        "value": false
      },
      "damage": {
        "value": false
      },
      "hrZero": {
        "value": false
      }
    },
    "attributes": {
      "primary": {
        "value": "ins"
      },
      "secondary": {
        "value": "mig"
      }
    },
    "accuracy": {
      "value": 0
    },
    "damage": {
      "hasDamage": {
        "value": false
      },
      "value": 0,
      "type": {
        "value": "physical"
      }
    },
    "impdamage": {
      "hasImpDamage": {
        "value": false
      },
      "value": 0,
      "impType": {
        "value": "minor"
      },
      "type": {
        "value": "physical"
      }
    },
    "hasResource": {
      "value": false
    },
    "rp": {
      "name": "Name",
      "current": 0,
      "step": 1,
      "max": 6
    },
    "requirement": {
      "value": "Sharpshooter, Weaponmaster"
    },
    "benefits": {
      "resources": {
        "hp": {
          "value": false
        },
        "mp": {
          "value": false
        },
        "ip": {
          "value": false
        }
      }
    },
    "source": {
      "value": "FUTF177"
    },
    "fuid": "quick-scan"
  },
  "effects": [],
  "flags": {
    "core": {}
  },
  "_stats": {
    "systemId": "projectfu",
    "systemVersion": "#{VERSION}#",
    "coreVersion": "13.346",
    "createdTime": 1711473807263,
    "modifiedTime": 1724180863690,
    "lastModifiedBy": "dobQfkKFj2NK96cc",
    "compendiumSource": null,
    "duplicateSource": null,
    "exportSource": null
  },
  "ownership": {
    "default": 0,
    "BwRsFvMHAq9vUtEO": 3
  },
  "_id": "6UzPwOYtyU0inH48",
  "sort": 0,
  "_key": "!items!6UzPwOYtyU0inH48"
}
