{
  "name": "Status Pierce (Poisoned)",
  "type": "effect",
  "img": "systems/projectfu/styles/static/statuses/Blank.webp",
  "system": {
    "fuid": "effect",
    "cost": {
      "value": 700
    }
  },
  "effects": [
    {
      "disabled": false,
      "name": "Status Pierce (Poisoned)",
      "img": "systems/projectfu/styles/static/statuses/Blank.webp",
      "type": "base",
      "changes": [],
      "description": "<p>All damage you deal to <strong>poisoned</strong> creatures ignores Resistances.</p>",
      "tint": "#ffffff",
      "transfer": true,
      "statuses": [],
      "sort": 0,
      "flags": {
        "projectfu": {
          "type": "quality",
          "subtype": "Offensive",
          "CrisisInteraction": "none",
          "source": "FUCR286"
        }
      },
      "_id": "Z7nsc9B263IVSBot",
      "system": {},
      "duration": {
        "startTime": null,
        "seconds": null,
        "combat": null,
        "rounds": null,
        "turns": null,
        "startRound": null,
        "startTurn": null
      },
      "origin": null,
      "_stats": {
        "compendiumSource": null,
        "duplicateSource": null,
        "coreVersion": "13.346",
        "systemId": "projectfu",
        "systemVersion": "#{VERSION}#",
        "createdTime": null,
        "modifiedTime": 1728775046775,
        "lastModifiedBy": "7kOzP8RBVJhI8wKx",
        "exportSource": null
      },
      "_key": "!items.effects!A0skwCyrYpLZcEmN.Z7nsc9B263IVSBot"
    }
  ],
  "folder": "SH8cHX3lJkZlLgj8",
  "flags": {},
  "_stats": {
    "compendiumSource": null,
    "duplicateSource": null,
    "coreVersion": "13.346",
    "systemId": "projectfu",
    "systemVersion": "#{VERSION}#",
    "createdTime": 1728747193107,
    "modifiedTime": 1728747193107,
    "lastModifiedBy": "7kOzP8RBVJhI8wKx",
    "exportSource": null
  },
  "_id": "A0skwCyrYpLZcEmN",
  "sort": 3700000,
  "ownership": {
    "default": 0,
    "7kOzP8RBVJhI8wKx": 3
  },
  "_key": "!items!A0skwCyrYpLZcEmN"
}
