{
  "folder": "OcoOq5td7Ya9GOPU",
  "name": "Turbo Module",
  "type": "classFeature",
  "img": "icons/commodities/tech/dial-meter-gauge-blue.webp",
  "system": {
    "summary": {
      "value": ""
    },
    "isFavored": {
      "value": false
    },
    "featureType": "projectfu.supportModule",
    "data": {
      "description": "<p><span style=\"font-family: 'PT Sans Narrow', sans-serif\">While driving this <strong>personal vehicle</strong>, you gain a +2 bonus to all Opposed Checks that rely on <strong style=\"box-sizing: border-box; user-select: text; color: rgb(43, 74, 66); font-family: 'PT Sans Narrow', sans-serif; font-size: 16px; font-style: normal; font-variant-ligatures: normal; font-variant-caps: normal; letter-spacing: normal; orphans: 2; text-align: start; text-indent: 0px; text-transform: none; white-space: normal; widows: 2; word-spacing: 0px; -webkit-text-stroke-width: 0px; text-decoration-thickness: initial; text-decoration-style: initial; text-decoration-color: initial;\">speed</strong> and <strong style=\"box-sizing: border-box; user-select: text; color: rgb(43, 74, 66); font-family: 'PT Sans Narrow', sans-serif; font-size: 16px; font-style: normal; font-variant-ligatures: normal; font-variant-caps: normal; letter-spacing: normal; orphans: 2; text-align: start; text-indent: 0px; text-transform: none; white-space: normal; widows: 2; word-spacing: 0px; -webkit-text-stroke-width: 0px; text-decoration-thickness: initial; text-decoration-style: initial; text-decoration-color: initial;\">rapid maneuvers</strong>.</span></p>",
      "complex": false
    },
    "source": "FUTF169"
  },
  "effects": [],
  "flags": {
    "core": {}
  },
  "_stats": {
    "systemId": "projectfu",
    "systemVersion": "#{VERSION}#",
    "coreVersion": "11.315",
    "createdTime": 1711477122275,
    "modifiedTime": 1719173179841,
    "lastModifiedBy": "BwRsFvMHAq9vUtEO"
  },
  "_id": "OEgMfny6AwrXCkEg",
  "sort": 0,
  "ownership": {
    "default": 0,
    "BwRsFvMHAq9vUtEO": 3
  },
  "_key": "!items!OEgMfny6AwrXCkEg"
}
